{
"type": "FeatureCollection",
"name": "etablissement-technique",
"crs": { "type": "name", "properties": { "name": "urn:ogc:def:crs:OGC:1.3:CRS84" } },
"features": [
{ "type": "Feature", "properties": { "id": 1, "Nom": "ESTBBTP – École Supérieure de BTP & Électricité", "Commune": "Gandon", "X": 346546.558, "Y": 1774385.329 }, "geometry": { "type": "Point", "coordinates": [ -16.434447188962931, 16.044469367382089 ] } }
]
}
