{
"type": "FeatureCollection",
"name": "établissement-technique",
"crs": { "type": "name", "properties": { "name": "urn:ogc:def:crs:OGC:1.3:CRS84" } },
"features": [
{ "type": "Feature", "properties": { "id": 1, "Nom": "Lycée Technique André Peytavin (LTAP)", "Commune": "SAINT-LOUIS", "X": 340528.454, "Y": 1771610.562 }, "geometry": { "type": "Point", "coordinates": [ -16.49050320977382, 16.019009140251033 ] } }
]
}
