{
"type": "FeatureCollection",
"name": "galerie-d'art",
"crs": { "type": "name", "properties": { "name": "urn:ogc:def:crs:OGC:1.3:CRS84" } },
"features": [
{ "type": "Feature", "properties": { "ID": "1", "Type": "Gallerie", "Nom": "Chez Gaël", "Nom Commun": "SAINT-LOUIS", "X": 339102.08, "Y": 1772779.504 }, "geometry": { "type": "Point", "coordinates": [ -16.5039107, 16.0294802 ] } }
]
}
